toga/__init__.py
toga/app.py
toga/colors.py
toga/command.py
toga/dialogs.py
toga/documents.py
toga/fonts.py
toga/handlers.py
toga/icons.py
toga/images.py
toga/keys.py
toga/paths.py
toga/platform.py
toga/py.typed
toga/screens.py
toga/statusicons.py
toga/types.py
toga/validators.py
toga/window.py
toga/constants/__init__.py
toga/hardware/__init__.py
toga/hardware/camera.py
toga/hardware/location.py
toga/plugins/__init__.py
toga/plugins/image_formats.py
toga/resources/__init__.py
toga/sources/__init__.py
toga/sources/accessors.py
toga/sources/base.py
toga/sources/list_source.py
toga/sources/tree_source.py
toga/sources/value_source.py
toga/style/__init__.py
toga/style/applicator.py
toga/style/pack.py
toga/widgets/__init__.py
toga/widgets/activityindicator.py
toga/widgets/base.py
toga/widgets/box.py
toga/widgets/button.py
toga/widgets/canvas.py
toga/widgets/dateinput.py
toga/widgets/detailedlist.py
toga/widgets/divider.py
toga/widgets/imageview.py
toga/widgets/label.py
toga/widgets/mapview.py
toga/widgets/multilinetextinput.py
toga/widgets/numberinput.py
toga/widgets/optioncontainer.py
toga/widgets/passwordinput.py
toga/widgets/progressbar.py
toga/widgets/scrollcontainer.py
toga/widgets/selection.py
toga/widgets/slider.py
toga/widgets/splitcontainer.py
toga/widgets/switch.py
toga/widgets/table.py
toga/widgets/textinput.py
toga/widgets/timeinput.py
toga/widgets/tree.py
toga/widgets/webview.py
toga_core-0.4.9.dist-info/LICENSE
toga_core-0.4.9.dist-info/METADATA
toga_core-0.4.9.dist-info/WHEEL
toga_core-0.4.9.dist-info/entry_points.txt
toga_core-0.4.9.dist-info/top_level.txt
toga_core-0.4.9.dist-info/RECORD
