Metadata-Version: 2.1
Name: toga-core
Version: 0.4.9
Summary: A Python native, OS native GUI toolkit.
Author-email: Russell Keith-Magee <russell@keith-magee.com>
Maintainer-email: BeeWare Team <team@beeware.org>
License: New BSD
Project-URL: Homepage, https://beeware.org/project/projects/libraries/toga/
Project-URL: Funding, https://beeware.org/contributing/membership/
Project-URL: Documentation, https://toga.readthedocs.io/
Project-URL: Tracker, https://github.com/beeware/toga/issues
Project-URL: Source, https://github.com/beeware/toga
Project-URL: Changelog, https://toga.readthedocs.io/en/stable/background/project/releases.html
Keywords: gui,widget,cross-platform,toga,desktop,mobile,web,macOS,cocoa,iOS,android,windows,winforms,linux,freeBSD,gtk,console,web
Classifier: Development Status :: 4 - Beta
Classifier: Intended Audience :: Developers
Classifier: License :: OSI Approved :: BSD License
Classifier: Operating System :: OS Independent
Classifier: Programming Language :: Python :: 3
Classifier: Programming Language :: Python :: 3.9
Classifier: Programming Language :: Python :: 3.10
Classifier: Programming Language :: Python :: 3.11
Classifier: Programming Language :: Python :: 3.12
Classifier: Programming Language :: Python :: 3.13
Classifier: Programming Language :: Python :: 3 :: Only
Classifier: Topic :: Software Development
Classifier: Topic :: Software Development :: User Interfaces
Classifier: Topic :: Software Development :: Widget Sets
Requires-Python: >=3.9
License-File: LICENSE
Requires-Dist: travertino<0.4.0,>=0.3.0
Requires-Dist: importlib_metadata>=4.4.0; python_version <= "3.9"
Provides-Extra: dev
Requires-Dist: coverage[toml]==7.6.2; extra == "dev"
Requires-Dist: coverage-conditional-plugin==0.9.0; extra == "dev"
Requires-Dist: Pillow==10.4.0; extra == "dev"
Requires-Dist: pre-commit==4.0.1; extra == "dev"
Requires-Dist: pytest==8.3.3; extra == "dev"
Requires-Dist: pytest-asyncio==0.24.0; extra == "dev"
Requires-Dist: pytest-freezer==0.4.8; extra == "dev"
Requires-Dist: setuptools-scm==8.1.0; extra == "dev"
Requires-Dist: tox==4.21.2; extra == "dev"
Requires-Dist: typing-extensions==4.12.2; python_version < "3.10" and extra == "dev"
Provides-Extra: docs
Requires-Dist: furo==2024.8.6; extra == "docs"
Requires-Dist: Pillow==10.4.0; extra == "docs"
Requires-Dist: pyenchant==3.2.2; extra == "docs"
Requires-Dist: sphinx==8.1.3; extra == "docs"
Requires-Dist: sphinx_tabs==3.4.5; extra == "docs"
Requires-Dist: sphinx-autobuild==2024.10.3; extra == "docs"
Requires-Dist: sphinx-csv-filter==0.4.2; extra == "docs"
Requires-Dist: sphinx-copybutton==0.5.2; extra == "docs"
Requires-Dist: sphinx-toolbox==3.8.1; extra == "docs"
Requires-Dist: sphinxcontrib-spelling==8.0.0; extra == "docs"
